{"slug":"daily-01x7XJLe","word":"chacareira","words":["aca","acá","aça","aia","ara","ará","are","chá","chã","eia","era","ira","rei","ria","rir","açaí","acha","acra","acre","arar","arca","área","ária","arre","caca","caça","cair","cara","cará","cear","ceia","cera","ciar","crer","cria","eira","hera","içar","irar","irra","raça","raer","raia","rara","rica","achar","aerar","araçá","arara","arcar","arear","areia","caçar","caiar","cárie","carrê","cerca","cheia","chiar","chica","craca","criar","raiar","acácia","acarar","acerca","arraia","careca","cercar","checar","crachá","eriçar","rachar","recair","ricaça","acercar","arcaica","cachear","caiçara","careira","chácara","cheirar","rechaçar","chacareira"],"definitions":{"acarar":"Olhar de frente.","acerca":"A pouca distância.","acha":"Quem procura (?)' (dito).","achar":"Encontrar (por acaso ou não).","arca":"(?) de Noé: salvou os animais.","área":"(?) de serviço, cômodo da casa.","arraia":"Rabo de (?), golpe de capoeira.","cachear":"Produzir cachos.","cair":"(?) bem: ser bem aceito.","cara":"(?)-de-pau: cínico.","careca":"Indivíduo calvo.","cear":"Comer a ceia.","cera":"Fazer (?): atrasar a partida (fut.).","cercar":"Fazer cerca a.","chácara":"Pequena propriedade rural, normalmente perto da cidade.","checar":"Conferir, verificar.","cheirar":"Aspirar o cheiro de.","chiar":"Produzir um som agudo e penetrante.","criar":"Dar existência a.","era":"Já (?): acabou.","eriçar":"Arrepiar, ouriçar.","hera":"Deusa grega da família (mit.).","içar":"Alçar, erguer, levantar.","ira":"Cólera, fúria, indignação.","raça":"Espírito de luta (fut.).","rachar":"Partir em estilhaços.","raiar":"Ao (?) do dia: ao amanhecer.","recair":"Cair outra vez.","rechaçar":"Combater, lutar contra, afastar.","rei":"Peça mais importante do jogo de xadrez.","rica":"Costa (?), país da América Central.","ricaça":"Mulher muito rica.","rir":"(?) é o melhor remédio (dito).","aca":"Cheiro ruim; fedor.","acá":"O mesmo que aqui.","aça":"Diz-se de pessoa ou animal albino.","ara":"Pedra do altar.","ará":"Arara.","are":"Unidade de medida de área equivalente a 100 metros quadrados.","ária":"Composição musical para uma só voz com acompanhamento de orquestra.","arre":"Voz com que se tocam animais de carga.","eia":"Que serve para animar, excitar.","eira":"Porção de terreno plano e duro, ou laje, em que se secam cereais e legumes.","raer":"Rapar e juntar o sal nas salinas.","acra":"Frágil, quebradiço (fem.).","aerar":"Colocar ar em algo.","aia":"Dama de companhia.","arar":"Lavrar (a terra) com arado.","arara":"Ave tropical da família dos psitacídeos.","arcar":"Dar forma de arco a.","arear":"Limpar ou polir panela(s).","açaí":"Fruta geralmente consumida com granola.","caça":"Desporto que consiste em caçar animais.","caçar":"Perseguir uma presa e, usualmente, matá-la.","caiar":"Pintar com cal diluída em água, só ou misturada com cola e/ou tinta.","ceia":"A última refeição do dia.","chá":"Bebida quente popular na Inglaterra.","chã":"Área ou extensão plana de terra.","ciar":"Mover-se para trás.","crer":"Ter como verdadeiro.","cria":"Animal que ainda mama.","rara":"Que existe em pouca quantidade (fem.).","ria":"Enseada estreita, produto do alagamento de um vale fluvial em épocas geológicas pretéritas.","araçá":"Fruto do araçazeiro.","cará":"Raíz comestível, muito parecida com o inhame.","irar":"Provocar a ira de.","irra":"Interjeição que expressa um sentimento de desabafo."}}