{"slug":"daily-D2Q08Ko1","word":"gravatas","words":["agá","ara","ará","asa","ata","gás","rãs","vãs","agás","agra","asar","atar","atas","gata","rasa","rata","saga","satã","tara","trás","vaga","vara","ágata","atrás","avara","gasta","gatas","grata","rasta","ratas","taras","trava","vagar","vagas","varas","vasta","ágatas","avaras","avatar","gastar","gratas","gravata","gravatas"],"definitions":{"asa":"(?)-delta, veículo do vôo livre.","gás":"Ânimo (fig.).","gastar":"Consumir, destruir.","gata":"Mulher muito bonita (gír.).","gravata":"Acessório de tecido usado em volta do pescoço.","trás":"Depois de.","vaga":"Espaço que não se encontra ocupado e pode vir a sê-lo.","vagar":"Andar sem destino.","vara":"Utensílio da pesca.","ara":"Pedra do altar.","ará":"Arara.","asar":"Prover de asa(s).","ata":"Registro escrito do que se passou em uma reunião.","atar":"Cingir, apertar ou atrelar.","rãs":"Anfíbio da ordem dos anuros que possui pele lisa (pl.).","rasa":"Antiga unidade de medida de volume para secos.","rata":"Fêmea do rato.","tara":"Abatimento no peso de mercadorias, atendendo-se ao vaso ou envoltório onde estão acondicionados.","agá":"Nome da oitava letra do alfabeto latino.","agás":"Nome da oitava letra do alfabeto latino (pl.).","atas":"Registro escrito do que se passou em uma reunião (pl.).","avara":"Avarento; somítico; mesquinho (fem.).","vãs":"Que não tem conteúdo (fem. pl.).","agra":"Acre, azedo, ácido (fem.).","atrás":"No lugar precedente."}}