{"slug":"daily-0ebpnJg2","word":"lambuzado","words":["aba","ado","ala","alô","ama","amo","azo","baú","boa","bom","dom","dum","duo","loa","lua","luz","mal","mão","mau","mol","oba","ola","olá","ulo","uma","alão","alma","amuo","aula","aulo","azul","bala","boda","bola","buda","bula","dama","doma","dual","duma","lado","lama","loba","mala","moda","mola","muda","mudo","mula","abalo","adubo","alado","álamo","álbum","amado","audaz","balão","dolmã","lauda","laudo","malão","azulão","badalo","bolada","lambda","azulado","lombada","lambuzado"],"definitions":{"ala":"Conjunto de objetos dispostos de maneira a formar uma linha.","alado":"Dotado de asas.","ama":"(?) de leite: amamenta criança alheia.","azulão":"Tom forte de azul.","baú":"Caixa com o tesouro de piratas.","bola":"(?) de cristal, objeto de videntes.","dom":"Bem ou graça recebida de divindade.","duo":"Dueto.","lado":"Parte esquerda ou direita de qualquer corpo.","lama":"Mistura heterogênea de terra e água.","lambda":"A 11ª letra do alfabeto grego.","lambuzado":"Emporcalhado, sujo.","lua":"(?) de mel: viagem de núpcias.","mal":"(?)-agradecido: ingrato, desagradecido (bras.).","mudo":"Pessoa que não consegue falar.","mula":"(?) sem cabeça, ente folclórico.","uma":"Artigo indefinido que individualiza, de modo indeterminado, o substantivo (fem.).","dama":"Mulher educada.","mala":"É utilizada para guardar roupas em viagens","alô":"Expressa saudação ao telefone.","loa":"Louvor fictício, mentira.","olá":"Usado como saudação ou como chamamento.","audaz":"Que tem audácia.","ado":"O leite fresco, recentemente ordenhado.","alma":"Parte espiritual do homem.","amo":"Dono da casa (em relação aos criados).","aula":"Lição de uma disciplina.","azo":"Motivo, causa; oportunidade.","azul":"A cor do oceano, do céu.","boa":"Ideal, apropriado (fem.).","boda":"Celebração de um casamento.","bolada":"Pancada com bola.","bom":"Moralmente correto em suas atitudes, de acordo com quem julga.","aba":"Borda de chapéu.","mão":"Extremidade do membro anterior dos primatas, capaz de manipular objetos.","mau":"Que não é de boa qualidade, ruim.","mol":"Massa molecular de uma substância expressa em gramas.","oba":"Expressão usada em algumas regiões brasileiras e que indica alegria, contentamento, surpresa.","ola":"Coreografia de torcidas em que os torcedores se levantam em sequência, como uma onda.","ulo":"Grito de sofrimento, aflição.","aulo":"Instrumento semelhante a um oboé duplo usado na Grécia antiga.","bula":"Impresso que acompanha um medicamento e que contém as indicações necessárias para o respectivo uso.","dual":"Composto de duas partes.","dum":"De um único.","luz":"Única radiação captada pelo olho humano.","laudo":"Texto contendo parecer técnico.","moda":"Tendência de consumo da atualidade.","doma":"Ato, processo ou efeito de domar.","lombada":"Parte da encadernação que cobre o dorso do livro."}}