{"slug":"daily-4enBLZeX","word":"casacões","words":["aca","acá","aça","aço","aos","asa","cão","cãs","coa","cós","eco","oca","são","sãs","sós","ação","acas","aços","asas","asca","asco","ases","caca","caça","caco","cães","caos","casa","caso","coca","coça","ecos","essa","ocas","saca","saco","sãos","seca","seco","acaso","acesa","aceso","ações","ascas","ascos","cação","cacas","caças","cacos","casas","casca","casco","casos","cocas","coesa","óssea","sacão","sacas","sacos","seção","secas","secos","acasos","acesas","acesos","acesso","casaco","cascão","cascas","cascos","cessão","coesas","acessão","casacos","casacões","cessação"],"definitions":{"acaso":"Fato imprevisto.","acasos":"Fato imprevisto (pl.).","aceso":"Que se acendeu.","acesso":"Entrada, ingresso.","aço":"(?) inox, material de pias e panelas.","aos":"(?) poucos: gradualmente.","asa":"(?)-delta, veículo do vôo livre.","ases":"Experientes em uma atividade (fig.).","casa":"(?) de detenção: prisão.","casaco":"Jaqueta.","cascão":"Casca dura e grossa.","cascos":"Superfícies duras.","caso":"Aventura amorosa (pop.).","cessão":"Ato de ceder.","saca":"(?)-rolhas: abre garrafas de vinho.","seção":"Porção retirada de um todo.","seco":"Sem água ou umidade.","cão":"Animal considerado o melhor amigo do homem.","aca":"Cheiro ruim; fedor.","acá":"O mesmo que aqui.","aça":"Diz-se de pessoa ou animal albino.","acas":"Cheiro ruim; fedor (pl.).","asca":"Repulsa violenta.","cãs":"Cabelos brancos.","coa":"Porção de líquido coado.","cós":"Pedaço de tecido que envolve a cintura em calças, saias, bermudas.","são":"Aquele que foi canonizado.","sãs":"Aquele que tem saúde (fem. pl.).","asas":"Membro de um animal que serve para o voo (pl.).","ação":"Papel que representa parte do valor do capital de uma sociedade anônima (econ.).","ações":"Papel que representa parte do valor do capital de uma sociedade anônima (econ.) (pl.).","caça":"Desporto que consiste em caçar animais.","cação":"Tipo de tubarão.","caco":"Fragmento ou pedaço quebrado de louça, barro ou vidro.","cacos":"Fragmento ou pedaço quebrado de louça, barro ou vidro (pl.).","cães":"Cachorro (pl.).","casas":"Construção que serve de moradia (pl.).","coça":"Surra, sova.","eco":"Repetição de um som refletido por um corpo.","oca":"Cabana rústica construída pelos indígenas do Brasil.","ocas":"Cabana rústica construída pelos indígenas do Brasil (pl.).","sós":"Solitário, sem companhia, sem círculo social (pl.).","asco":"Nojo, repugnância."}}