{"slug":"daily-YPLq3aye","word":"linhaça","words":["aca","acá","aça","aia","ala","ali","anã","cal","chá","chã","clã","lai","lha","lia","açaí","acha","alça","aliá","anal","anca","anil","cana","ilha","inca","laca","laia","naca","nica","anciã","calha","canal","canil","laica","lança","liana","linha","linhaça"],"definitions":{"acha":"Quem procura (?)' (dito).","ala":"Conjunto de objetos dispostos de maneira a formar uma linha.","anca":"Garupa de animal.","cana":"(?)-de-açúcar: é a matéria-prima do etanol.","canal":"(?) de Suez, localiza-se no Egito.","linha":"Fio de um tecido qualquer.","laia":"Classe, espécie, tipo.","aca":"Cheiro ruim; fedor.","acá":"O mesmo que aqui.","aça":"Diz-se de pessoa ou animal albino.","anã":"Mulher de estatura muito abaixo do normal.","cal":"Pó branco constituído principalmente de óxido ou hidróxido de cálcio.","inca":"Indígena dos Incas.","nica":"Melindre exagerado.","aia":"Dama de companhia.","aliá":"Fêmea do elefante.","anal":"Relativo ao ânus.","anciã":"Mulhere idosa.","anil":"Diz-se de certa tonalidade de azul.","açaí":"Fruta geralmente consumida com granola.","chá":"Bebida quente popular na Inglaterra.","chã":"Área ou extensão plana de terra.","clã":"Grupo de famílias que se consideram descendentes dos mesmos ancestrais.","laca":"Resina ou goma resinosa obtida de certas árvores no oriente.","lai":"Pequeno poema da Idade Média, narrativo ou lírico, em versos octossilábicos.","lia":"Resquício sujo.","liana":"Nome genérico de trepadeiras da zona tropical, lenhosas e sarmentosas.","ilha":"Porção de terra emersa cercada de água.","lha":"Pronome oblíquo feminino."}}