{"slug":"daily-4emgg42w","word":"anciãs","words":["aca","acá","aça","aia","ais","anã","asa","cãs","nas","siá","açaí","acas","aias","anãs","anca","anis","asca","asna","cais","cana","casa","inca","isca","naca","nica","saca","saci","saia","sica","sina","açaís","anais","ancas","anciã","ânsia","canas","incas","nacas","anciãs","canais"],"definitions":{"anais":"Registros escritos da História (pop.).","anca":"Garupa de animal.","ancas":"Garupa de animal (pl.).","anciãs":"Mulheres idosas.","ânsia":"Ansiedade provocada principalmente pela dúvida.","asa":"(?)-delta, veículo do vôo livre.","cana":"(?)-de-açúcar: é a matéria-prima do etanol.","casa":"(?) de detenção: prisão.","isca":"Chamariz (fig.).","saca":"(?)-rolhas: abre garrafas de vinho.","saci":"(?)-Pererê, entidade folclórica brasileira.","sina":"Destino.","aca":"Cheiro ruim; fedor.","acá":"O mesmo que aqui.","aça":"Diz-se de pessoa ou animal albino.","acas":"Cheiro ruim; fedor (pl.).","anã":"Mulher de estatura muito abaixo do normal.","anis":"(?)-estrelado, especiaria.","asca":"Repulsa violenta.","asna":"Fêmea do jumento.","cais":"Parte de um porto onde se faz o embarque ou desembarque de pessoas ou mercadorias.","cãs":"Cabelos brancos.","inca":"Indígena dos Incas.","nas":"Contração da preposição em com o artigo feminino plural as.","nica":"Melindre exagerado.","siá":"Sinhá.","sica":"Punhal usado pelos antigos romanos.","aia":"Dama de companhia.","aias":"Dama de companhia (pl.).","ais":"Expressa dor física ou sentimental (pl.).","anãs":"Mulher de estatura abaixo do normal (pl.).","anciã":"Mulhere idosa.","açaí":"Fruta geralmente consumida com granola."}}