{"slug":"daily-APRz7VP0","word":"arrojados","words":["ado","aos","ara","ará","aro","asa","dar","das","dor","dos","ora","rãs","ror","são","ados","adro","arar","aros","asar","doar","odor","orar","oras","raja","rajá","rara","raro","rasa","raso","roda","rodo","rosa","soar","soda","soja","soro","arado","ardor","asado","dorso","dosar","jarda","jarra","jarro","orada","radar","rajão","rajar","raras","raros","rasar","rodar","rodas","rodos","rojão","sarar","sarda","sarja","sóror","adorar","arador","arados","arraso","jardas","jarras","jarros","oradas","orador","rajado","rosada","rosado","sarado","oradora","ardorosa","arrojado","oradoras","arrojados"],"definitions":{"adorar":"Amar; gostar muito.","aos":"(?) poucos: gradualmente.","arador":"Aquele que ara.","arraso":"Causar grande estrago em.","asa":"(?)-delta, veículo do vôo livre.","doar":"Transferir a posse de algo, gratuitamente, para outrem.","dorso":"As costas do homem (anat.).","jardas":"Unidade de comprimento básica nos sistemas de medida utilizados nos Estados Unidos e no Reino Unido (pl.).","jarro":"Vasilha de corpo grosso e boca larga, geralmente com uma só asa.","odor":"Cheiro.","orador":"Aquele que discursa em público.","oradora":"Aquele que discursa em público (fem.).","raro":"Que existe em pouca quantidade.","raso":"Não profundo.","roda":"(?)-gigante, presente em parques de diversão.","rodo":"A (?): à beça.","rosa":"A Rainha das Flores.","rosado":"Cor de rosa.","sarado":"Forte (gír.).","sarda":"Manchinha da pele dos ruivos.","soar":"Produzir ou emitir som.","soda":"(?) cáustica: é usada em limpeza.","dar":"Transferir a posse de algo, gratuitamente, para outrem.","ara":"Pedra do altar.","ará":"Arara.","aro":"Arco; argola; círculo; anel.","asar":"Prover de asa(s).","das":"Contração da preposição da com o artigo definido feminino plural as.","ora":"Agora.","rãs":"Anfíbio da ordem dos anuros que possui pele lisa (pl.).","rasa":"Antiga unidade de medida de volume para secos.","são":"Aquele que foi canonizado.","sarja":"Tecido entrançado de lã, seda ou algodão.","ado":"O leite fresco, recentemente ordenhado.","adro":"Espaço em volta das igrejas.","arar":"Lavrar (a terra) com arado.","asado":"Que tem asas.","dor":"Sofrimento físico ou moral.","orada":"Local onde se reza.","orar":"Rezar.","rara":"Que existe em pouca quantidade (fem.).","ror":"Grande quantidade (pop.).","soro":"Líquido que se separa do leite, quando este se coagula.","ados":"O leite fresco, recentemente ordenhado (pl.).","arado":"Instrumento agrícola usado para lavrar a terra.","arados":"Instrumento agrícola usado para lavrar a terra (pl.).","dosar":"Dividir (algo) em doses.","jarra":"Vaso para flores ou para ornato."}}