{"slug":"daily-617Br73e","word":"amante","words":["ama","anã","ata","até","ema","eta","mãe","nem","anta","ante","mana","mané","mata","mate","meta","nata","neta","tema","amena","manta","menta","amante","maneta"],"definitions":{"ama":"(?) de leite: amamenta criança alheia.","amante":"Aquele que ama.","até":"(?) logo, saudação de despedida.","mané":"Indivíduo desleixado, negligente.","maneta":"Aquele a quem lhe falta uma das mãos.","mate":"Erva usada para fazer um chá típico da região sul brasileira.","meta":"Objetivo a ser alcançado.","nata":"Camada de gordura que se forma à superfície do leite.","nem":"(?) tudo que reluz é ouro (dito).","tema":"Assunto.","mãe":"Progenitora, a que dá à luz.","anã":"Mulher de estatura muito abaixo do normal.","ata":"Registro escrito do que se passou em uma reunião.","ema":"Grande ave parecida com o avestruz.","eta":"Sétima letra do alfabeto grego.","anta":"O maior mamífero brasileiro.","ante":"Em frente a, perante.","mana":"Irmã (infrm.).","neta":"Filha do filho ou filha."}}