{"slug":"daily-VPd6Eg14","word":"jogatina","words":["agá","aia","aio","anã","ano","ata","ato","gin","íon","ita","itã","não","noa","oti","tão","tia","tio","ágio","anão","anja","anjo","anta","anti","gaja","gajo","gana","gata","gato","gota","ingá","ioga","iota","jato","joia","jota","naja","nata","nato","nota","tani","tina","tino","toga","tona","agito","antão","átona","gaita","inata","inato","jinga","tanga","tango","agonia","antiga","antigo","gaiato","goiana","ignota","janota","jogatina"],"definitions":{"ágio":"Lucro obtido em operações de câmbio.","agonia":"Aflição, angústia.","anjo":"Ser espiritual que serve de mensageiro entre Deus e os homens.","anti":"(?)-horário, o sentido oposto ao do relógio.","antiga":"Que existiu no passado (fem.).","antigo":"Que existe há muito tempo.","gaiato":"Rapaz travesso e vadio (gíria).","gaita":"Instrumento de sopro.","gata":"Mulher muito bonita (gír.).","goiana":"Habitante de Goiás (fem.).","inato":"Que nasce com o indivíduo.","ioga":"Exercícios praticados a partir dos ensinamentos filosóficos indianos.","jota":"Nome da décima letra do alfabeto latino.","nata":"Camada de gordura que se forma à superfície do leite.","nato":"Nativo de um país.","nota":"(?) fiscal: fatura.","tango":"Estilo de música e de dança muito comum na Argentina.","tia":"(?) Nastácia, personagem da obra de Monteiro Lobato.","tino":"Juízo natural; discernimento.","tio":"(?) Sam, símbolo dos Estados Unidos.","tona":"À (?): à superfície.","aio":"Criado particular; escudeiro.","anã":"Mulher de estatura muito abaixo do normal.","ano":"(?) bissexto, tem 366 dias.","ata":"Registro escrito do que se passou em uma reunião.","íon":"Átomo ou grupo atômico eletricamente carregado.","ita":"Embarcação que fazia o percurso pela costa brasileira do norte e o sul do país.","não":"Expressa negação.","tão":"Tanto, com tal intensidade.","janota":"Elegante, muito enfeitado.","agá":"Nome da oitava letra do alfabeto latino.","aia":"Dama de companhia.","anão":"Homem de estatura muito abaixo do normal.","anta":"O maior mamífero brasileiro.","ato":"Algo que foi feito.","gin":"Bebida alcoólica feita à base de cereais, aromatizada com zimbro.","iota":"Nona letra do alfabeto grego.","itã":"Ornamento de pedra característico das urnas funerárias dos antigos povos aborígines.","noa":"Hora canônica do ofício divino entre a sexta e as vésperas (correspondente às três horas da tarde).","oti":"Aguardente de cana.","gana":"Grande apetite ou vontade.","gato":"Pequeno mamífero carnívoro doméstico da família dos felídeos.","toga":"Traje usado por magistrados.","ingá":"Fruto do ingazeiro."}}