{"slug":"daily-4eEbG3B1","word":"lagosta","words":["agá","ala","alô","aos","asa","ata","ato","gás","gol","lãs","loa","los","ola","olá","sal","são","sol","tal","tão","agás","alão","alas","alga","algo","alta","alto","atas","atol","atos","gala","galã","galo","gata","gato","gola","gols","gota","lago","lata","lato","loas","olas","saga","sala","satã","sola","tala","talo","toga","tola","tosa","algas","altas","altos","atlas","galão","galas","galos","gasta","gasto","gatas","gatos","golas","gotas","lagoa","lagos","latão","latas","salão","salto","solta","talão","talas","talos","togas","tolas","lagoas","lagosta"],"definitions":{"ala":"Conjunto de objetos dispostos de maneira a formar uma linha.","alas":"Ó Abre-(?), marcha carnavalesca.","alga":"(?) marinha, vegetal rico em iodo.","algo":"Alguma coisa.","alto":"De grande extensão vertical.","aos":"(?) poucos: gradualmente.","asa":"(?)-delta, veículo do vôo livre.","gala":"Traje de (?): é usado em cerimônias.","galã":"Homem belo, elegante.","galo":"O macho da galinha.","gás":"Ânimo (fig.).","gata":"Mulher muito bonita (gír.).","gol":"Momento mágico do futebol.","lago":"Acumulação permanente de água numa depressão.","lagoa":"(?) dos Patos, atração do Rio Grande do Sul.","lagoas":"Lago de pouca extensão (pl.).","lagosta":"Tipo de crustáceo.","lata":"Folha de ferro laminada e estanhada.","latão":"Liga de cobre e zinco.","los":"(?) Angeles, cidade da Califórnia dos EUA.","sala":"Local da casa para visitas.","salão":"Sala grande.","alô":"Expressa saudação ao telefone.","ata":"Registro escrito do que se passou em uma reunião.","loa":"Louvor fictício, mentira.","olá":"Usado como saudação ou como chamamento.","são":"Aquele que foi canonizado.","tão":"Tanto, com tal intensidade.","agá":"Nome da oitava letra do alfabeto latino.","agás":"Nome da oitava letra do alfabeto latino (pl.).","alta":"De grande extensão vertical (fem).","atas":"Registro escrito do que se passou em uma reunião (pl.).","ato":"Algo que foi feito.","atol":"Ilha de forma anelar formada pela acumulação e consolidação de recifes de coral.","lãs":"Pelo espesso, frisado e macio que cobre o corpo de certos animais, especialmente carneiros e ovelhas (pl.).","loas":"Louvações em cantos religiosos.","ola":"Coreografia de torcidas em que os torcedores se levantam em sequência, como uma onda.","sal":"Condimento composto principalmente por cloreto de sódio.","sol":"Centro e principal astro do sistema solar.","tal":"Igual, semelhante.","gato":"Pequeno mamífero carnívoro doméstico da família dos felídeos.","gola":"Parte da roupa que cinge o pescoço ou está junto dele.","toga":"Traje usado por magistrados."}}