{"slug":"daily-VKw5N3km","word":"máquinas","words":["aia","ais","ama","anã","anu","asa","imã","ímã","mas","más","mau","mui","nas","nau","nua","num","nus","siá","sim","sua","suã","uai","uma","uns","aias","amas","anãs","anis","anus","ânus","aqui","asma","asna","imãs","ímãs","maia","mais","mana","maus","miau","mina","musa","naus","nuas","numa","saia","sina","suma","umas","anais","ânsia","maias","manas","mania","mansa","miaus","minas","numas","quais","quina","sauna","suína","usina","anuais","manias","quinas","manuais","máquina","máquinas"],"definitions":{"ama":"(?) de leite: amamenta criança alheia.","amas":"(?) de leite: amamenta criança alheia (pl.).","anais":"Registros escritos da História (pop.).","ânsia":"Ansiedade provocada principalmente pela dúvida.","anuais":"Que dura um ano (pl.).","aqui":"Neste ou a este lugar.","asa":"(?)-delta, veículo do vôo livre.","imã":"Coisa que atrai (fig.).","maias":"Povo indígena da América Central e parte do México.","mais":"Acima de.","mania":"Prática repetitiva.","maia":"Indivíduo dos maias.","nau":"Antiga embarcação a vela.","sauna":"Uma espécie de banho de vapor.","sina":"Destino.","umas":"(?) e outras: doses de bebidas.","usina":"(?) nuclear, produz eletricidade a partir de energia nuclear.","uma":"Artigo indefinido que individualiza, de modo indeterminado, o substantivo (fem.).","mina":"Escavação no solo destinada a extração de minerais.","anã":"Mulher de estatura muito abaixo do normal.","anis":"(?)-estrelado, especiaria.","asna":"Fêmea do jumento.","nas":"Contração da preposição em com o artigo feminino plural as.","siá":"Sinhá.","uai":"Expressa surpresa, espanto.","aia":"Dama de companhia.","aias":"Dama de companhia (pl.).","ais":"Expressa dor física ou sentimental (pl.).","anãs":"Mulher de estatura abaixo do normal (pl.).","anu":"Nome comum a várias aves da família dos Cuculídeos.","ânus":"Orifício na extremidade final do intestino grosso, por onde são expelidos os excrementos.","asma":"Doença do aparelho respiratório (med.).","mana":"Irmã (infrm.).","mas":"Conjunção adversativa, indica clara oposição entre ideias.","mau":"Que não é de boa qualidade, ruim.","naus":"Antiga embarcação a vela (pl.).","nua":"Despido, em pelo, sem roupas (fem.).","nus":"Despido, em pelo, sem roupas (pl.).","sim":"Exprime afirmação, aprovação.","sua":"Pronome possessivo que corresponde à terceira pessoa gramatical (fem.).","suã":"Parte inferior do lombo do porco.","uns":"Artigo indefinido que individualiza, de modo indeterminado, o substantivo (pl.).","ímã":"Peça de metal imantada.","más":"Que não é de boa qualidade, ruim (fem. pl.).","mui":"Forma apocopada de muito."}}