{"slug":"daily-RPYagroP","word":"babuínos","words":["aio","ais","ano","anu","aos","baú","bis","boa","boi","íon","não","nas","nau","noa","nos","nós","nua","nus","oba","são","siá","sob","sua","suã","sub","uai","uno","uns","uso","abio","aios","anis","anos","anus","ânus","asno","baio","baús","boas","boba","boia","bois","bons","íons","nabo","naus","nuas","ônus","sano","sina","sino","abuso","baios","bisão","bobas","boias","boina","bônus","nabos","sábio","suína","suíno","união","usina","bobina","boinas","ônibus","babuíno","bobinas","babuínos"],"definitions":{"aos":"(?) poucos: gradualmente.","baú":"Caixa com o tesouro de piratas.","bis":"14-(?): foi construído por Santos Dumont.","boas":"(?)-festas, saudação natalina.","boi":"(?)-bumbá, festa popular brasileira.","boia":"Dispositivo flutuante.","boina":"Chapéu de lã ou pano semelhante a um boné, mas sem a aba.","nau":"Antiga embarcação a vela.","ônibus":"Meio de transporte coletivo.","sábio":"Aquele que sabe muito.","sina":"Destino.","usina":"(?) nuclear, produz eletricidade a partir de energia nuclear.","aio":"Criado particular; escudeiro.","anis":"(?)-estrelado, especiaria.","ano":"(?) bissexto, tem 366 dias.","íon":"Átomo ou grupo atômico eletricamente carregado.","não":"Expressa negação.","nas":"Contração da preposição em com o artigo feminino plural as.","são":"Aquele que foi canonizado.","siá":"Sinhá.","uai":"Expressa surpresa, espanto.","suíno":"Relativo ao porco.","ais":"Expressa dor física ou sentimental (pl.).","anos":"(?) Dourados, minissérie brasileira dos anos 80.","anu":"Nome comum a várias aves da família dos Cuculídeos.","ânus":"Orifício na extremidade final do intestino grosso, por onde são expelidos os excrementos.","asno":"Burro, jumento.","baio":"Da cor do ouro fosco e esmaecido, amarelado.","boa":"Ideal, apropriado (fem.).","boba":"Diz-se de pessoa que diz ou que faz bobagens (fem).","bois":"Touro capado (pl.).","bons":"Moralmente correto em suas atitudes, de acordo com quem julga (pl.).","naus":"Antiga embarcação a vela (pl.).","noa":"Hora canônica do ofício divino entre a sexta e as vésperas (correspondente às três horas da tarde).","nós":"Um grupo de pessoas, incluindo a si mesmo.","nua":"Despido, em pelo, sem roupas (fem.).","nus":"Despido, em pelo, sem roupas (pl.).","oba":"Expressão usada em algumas regiões brasileiras e que indica alegria, contentamento, surpresa.","sob":"Abaixo, em baixo.","sua":"Pronome possessivo que corresponde à terceira pessoa gramatical (fem.).","suã":"Parte inferior do lombo do porco.","uno":"Único.","uns":"Artigo indefinido que individualiza, de modo indeterminado, o substantivo (pl.).","uso":"Ato ou efeito de usar.","abio":"Fruto do abieiro.","nos":"Pronome pessoal átono, da primeira pessoa do plural.","união":"Ato de unir(-se).","bisão":"Boi selvagem encontrado na América do Norte e Europa."}}