{"slug":"daily-RP4LKKPK","word":"embocar","words":["aço","amo","are","aro","bar","bem","boa","bom","cão","cem","coa","com","cor","eco","ema","era","mãe","mão","mar","mor","oba","oca","ora","acém","acre","acro","amor","arco","baço","beca","beça","beco","boca","bôer","bora","broa","cabo","caro","cear","cera","coar","coma","cora","erma","ermo","maço","maré","meão","mear","mera","mero","moca","moça","moer","mora","obra","ocar","ocre","orbe","orca","rabo","ramo","reco","remo","robe","roca","roça","romã","barco","berço","braço","breca","broca","caber","cobra","cobre","comer","ecoar","macro","marco","março","acerbo","embora","embocar"],"definitions":{"acerbo":"Ácido, azedo.","aço":"(?) inox, material de pias e panelas.","arco":"A Arma de Robin Hood (lit.).","beco":"Rua estreita e curta, por vezes sem saída.","bem":"(?)-estar: conforto.","berço":"Pequeno leito para criança de colo.","boca":"O peixe morre pela (?) (dito).","braço":"Membro superior (anat.).","cabo":"(?) Frio, cidade do Rio de Janeiro.","caro":"Adjetivo com que se iniciam cartas.","cear":"Comer a ceia.","cera":"Fazer (?): atrasar a partida (fut.).","cobre":"É usado na fabricação do bronze.","cor":"Coloração predominante de algo.","ecoar":"Repercutir, soar.","embora":"Apesar de.","era":"Já (?): acabou.","maré":"Movimento periódico de subida e descida das águas do mar.","moça":"Mulher jovem.","moer":"Reduzir a pó por meio de moinho.","mor":"Altar-(?): o principal da igreja.","rabo":"(?) de cavalo, tipo de penteado.","cão":"Animal considerado o melhor amigo do homem.","mãe":"Progenitora, a que dá à luz.","are":"Unidade de medida de área equivalente a 100 metros quadrados.","aro":"Arco; argola; círculo; anel.","coa":"Porção de líquido coado.","ema":"Grande ave parecida com o avestruz.","ora":"Agora.","acro":"Frágil, quebradiço.","amo":"Dono da casa (em relação aos criados).","amor":"Sentimento de gostar muito de outra pessoa ou coisa.","baço":"Órgão linfático presente no corpo humano.","bar":"Estabelecimento que comercializa bebidas.","beca":"Vestimenta usada por magistrados e formandos.","boa":"Ideal, apropriado (fem.).","bôer":"Relativo aos descendentes de holandeses na África do Sul.","bom":"Moralmente correto em suas atitudes, de acordo com quem julga.","bora":"Expressão para convidar e induzir que se tome parte junto numa ação.","broa":"Pão ou bolo arredondado de farinha de milho, trigo etc.","caber":"Poder estar ou ser contido.","cem":"Número equivalente a dez dezenas.","com":"Preposição que indica junção.","eco":"Repetição de um som refletido por um corpo.","ermo":"Que está só ou desacompanhado.","erma":"Que está só ou desacompanhado (fem.).","maço":"Conjunto de coisas embaladas ou atadas.","mão":"Extremidade do membro anterior dos primatas, capaz de manipular objetos.","mar":"Grande quantidade de água salgada que cobre parte do planeta Terra.","mero":"Simples; genuíno.","moca":"Variedade de café fino, originário da Arábia..","oba":"Expressão usada em algumas regiões brasileiras e que indica alegria, contentamento, surpresa.","obra":"Edifício em construção.","oca":"Cabana rústica construída pelos indígenas do Brasil.","ocre":"Da cor da terra.","orca":"Certa espécie de cetáceo carnívoro, Orcinus orca.","ramo":"Divisão ou subdivisão de um caule (bot.).","reco":"Jovem que acabou de ser admitido ao serviço militar.","roca":"Cana ou vara preparada para fiar.","roça":"Terreno coberto de mato.","romã":"Fruto da romãzeira.","coar":"Fazer passar por filtro.","cora":"Ato de corar (roupa, cera, etc.).","remo":"Instrumento que serve para impulsionar pequenas embarcações pela força humana.","mera":"Simples; genuíno (fem.)."}}