{"slug":"daily-v2v088e4","word":"redução","words":["aço","ado","are","aro","auê","cão","céu","coa","cor","cru","dar","dor","duo","eco","era","oca","ode","ora","réu","rua","ura","acre","acro","adro","aedo","arco","cadê","cado","caro","cear","cedo","cera","coar","coda","cora","crua","cura","deão","doar","doca","doce","doer","dura","duro","euro","ocar","ocre","odre","orca","reco","roca","roça","roda","ruão","rude","urca","urco","açude","acuro","árduo","áureo","cardo","cedro","cerda","côdea","corda","credo","curdo","décor","durão","ecoar","erado","recuo","rouca","curado","doçura","educar","recado","recuado","redução"],"definitions":{"aço":"(?) inox, material de pias e panelas.","arco":"A Arma de Robin Hood (lit.).","árduo":"De difícil realização, trabalhoso.","auê":"Bagunça, confusão (gír.).","caro":"Adjetivo com que se iniciam cartas.","cear":"Comer a ceia.","cera":"Fazer (?): atrasar a partida (fut.).","céu":"A (?) aberto: ao ar livre.","cor":"Coloração predominante de algo.","curado":"Restabelecido de doença.","doar":"Transferir a posse de algo, gratuitamente, para outrem.","doce":"De sabor açucarado.","doçura":"Qualidade do que é doce.","doer":"Causar dor, sofrimento.","duo":"Dueto.","duro":"Sem dinheiro (gír.).","ecoar":"Repercutir, soar.","educar":"Ministrar educação a.","era":"Já (?): acabou.","recado":"Mensagem escrita ou oral.","redução":"Diminuição.","réu":"Acusado em juízo (jur.).","roda":"(?)-gigante, presente em parques de diversão.","rude":"Áspero, descortês.","urca":"Antiga embarcação larga.","cão":"Animal considerado o melhor amigo do homem.","dar":"Transferir a posse de algo, gratuitamente, para outrem.","aedo":"Cantor ambulante, trovador.","are":"Unidade de medida de área equivalente a 100 metros quadrados.","aro":"Arco; argola; círculo; anel.","coa":"Porção de líquido coado.","ode":"Composição poética do gênero lírico.","ora":"Agora.","ura":"Larva.","doca":"Parte de um porto onde as embarcações atracam.","acro":"Frágil, quebradiço.","ado":"O leite fresco, recentemente ordenhado.","adro":"Espaço em volta das igrejas.","cadê":"Forma interrogativa usada para perguntar onde algo ou alguém está.","cedo":"Antes da hora desejada ou costumeira.","cru":"Que não foi cozido.","dor":"Sofrimento físico ou moral.","eco":"Repetição de um som refletido por um corpo.","oca":"Cabana rústica construída pelos indígenas do Brasil.","ocre":"Da cor da terra.","odre":"Saco para transportar líquidos.","orca":"Certa espécie de cetáceo carnívoro, Orcinus orca.","reco":"Jovem que acabou de ser admitido ao serviço militar.","roca":"Cana ou vara preparada para fiar.","roça":"Terreno coberto de mato.","rua":"Na cidade, via pública urbana.","cedro":"Árvore conífera.","coar":"Fazer passar por filtro.","cora":"Ato de corar (roupa, cera, etc.).","euro":"Moeda única dos países da União Europeia."}}