{"slug":"daily-be3VZD6P","word":"certeza","words":["are","até","era","eta","ter","tez","acre","arte","ater","cear","cera","czar","éter","reta","reza","tear","tzar","catre","certa","ereta","tecer","terça","terçã","treze","certeza"],"definitions":{"até":"(?) logo, saudação de despedida.","cear":"Comer a ceia.","cera":"Fazer (?): atrasar a partida (fut.).","certeza":"Qualidade do que é certo.","era":"Já (?): acabou.","reta":"Linha, traço que segue sempre a mesma direção.","ter":"(?) os pés no chão: ser realista.","are":"Unidade de medida de área equivalente a 100 metros quadrados.","eta":"Sétima letra do alfabeto grego.","arte":"Atividade criadora.","ater":"Impedir que prossiga.","czar":"Título dado ao imperador da Rússia.","éter":"Líquido hipotético de sustentação celestial (fís).","tez":"Epiderme, pele, cútis.","catre":"Cama simples para uma só pessoa; leito rústico."}}