{"slug":"daily-Q2NLarek","word":"chefiar","words":["are","chá","chã","eia","era","ira","rei","ria","acre","café","cair","cear","ceia","cera","ciar","cria","eira","face","feia","fera","fiar","frei","fria","hera","içar","rica","rifa","cárie","ceifa","chefa","cheia","chiar","cifra","feira","féria","ficar","ceifar","chefia","fechar","fichar","frecha","chefiar"],"definitions":{"café":"(?) da manhã: desjejum.","cair":"(?) bem: ser bem aceito.","cear":"Comer a ceia.","ceifar":"Cortar com foice ou instrumento apropriado.","cera":"Fazer (?): atrasar a partida (fut.).","chefia":"Chefe, patrão.","chefiar":"Exercer a função de chefe.","chiar":"Produzir um som agudo e penetrante.","era":"Já (?): acabou.","face":"Parte do corpo humano onde se encontram os olhos, nariz e boca.","feira":"Local onde se mostram e vendem mercadorias.","fera":"A Bela e a (?)', conto infantil.","fiar":"Reduzir a fio.","ficar":"Permanecer num lugar.","fichar":"Anotar, registrar em fichas.","hera":"Deusa grega da família (mit.).","içar":"Alçar, erguer, levantar.","ira":"Cólera, fúria, indignação.","rei":"Peça mais importante do jogo de xadrez.","rica":"Costa (?), país da América Central.","rifa":"Sorteio de objetos por meio da loteria ou de bilhetes numerados.","are":"Unidade de medida de área equivalente a 100 metros quadrados.","eia":"Que serve para animar, excitar.","eira":"Porção de terreno plano e duro, ou laje, em que se secam cereais e legumes.","ceia":"A última refeição do dia.","chá":"Bebida quente popular na Inglaterra.","chã":"Área ou extensão plana de terra.","ciar":"Mover-se para trás.","cria":"Animal que ainda mama.","ria":"Enseada estreita, produto do alagamento de um vale fluvial em épocas geológicas pretéritas.","feia":"Desprovido de beleza (fem.)."}}