{"slug":"daily-mPldKJP5","word":"inépcia","words":["eia","ipê","pai","pia","piá","acne","ceia","cena","cepa","cine","inca","nica","pane","peça","peia","pena","pina","ápice","épica","naipe","penca","inépcia"],"definitions":{"acne":"Doença da pele.","pai":"(?)-nosso, oração cristã.","pane":"Parada, por falha dos motores, de automóvel, avião, motocicleta, etc.","pena":"Castigo; punição.","eia":"Que serve para animar, excitar.","inca":"Indígena dos Incas.","nica":"Melindre exagerado.","ceia":"A última refeição do dia.","cepa":"Tronco de videira (bot.).","ipê":"Árvore leguminosa com madeira avermelhada e floração de cor muito viva.","pia":"Recipiente de pedra para líquidos.","piá":"Criança do sexo masculino.","inépcia":"Falta de inteligência."}}