{"slug":"daily-m1Bb3J41","word":"sílica","words":["ais","ali","cal","cãs","clã","lai","lãs","lia","lis","sal","siá","cais","clãs","isca","islã","lais","lias","lisa","saci","sica","sílica"],"definitions":{"isca":"Chamariz (fig.).","islã":"O conjunto dos países islâmicos.","lis":"Flor-de-(?): lírio.","saci":"(?)-Pererê, entidade folclórica brasileira.","cais":"Parte de um porto onde se faz o embarque ou desembarque de pessoas ou mercadorias.","cal":"Pó branco constituído principalmente de óxido ou hidróxido de cálcio.","cãs":"Cabelos brancos.","siá":"Sinhá.","sica":"Punhal usado pelos antigos romanos.","ais":"Expressa dor física ou sentimental (pl.).","clã":"Grupo de famílias que se consideram descendentes dos mesmos ancestrais.","lai":"Pequeno poema da Idade Média, narrativo ou lírico, em versos octossilábicos.","lãs":"Pelo espesso, frisado e macio que cobre o corpo de certos animais, especialmente carneiros e ovelhas (pl.).","lia":"Resquício sujo.","sal":"Condimento composto principalmente por cloreto de sódio."}}