{"slug":"daily-NPABBoeD","word":"formando","words":["ado","amo","ano","aro","dar","dom","dor","mão","mar","mor","não","noa","ora","adro","afro","amor","dano","doar","doma","dona","dono","fado","faro","fora","foro","mano","moda","modo","mofo","mono","mora","nado","nodo","nora","odor","onda","órfã","ramo","roda","rodo","romã","andor","ânodo","domar","fardo","forma","forno","mando","mofar","morna","morno","nódoa","norma","órfão","ronda","rondó","adorno","amorfo","formão","namoro","ornado","romano","formado","morando","formando"],"definitions":{"adorno":"Aquilo que serve de enfeite ou ornamento.","amorfo":"Sem forma definida, sem estrutura.","dano":"Estrago, danificação.","doar":"Transferir a posse de algo, gratuitamente, para outrem.","dom":"Bem ou graça recebida de divindade.","dona":"Mulher casada; esposa.","fado":"Destino; sorte.","fora":"Bota-(?), festa de despedida.","forma":"Conjunto de superfícies que compõem um corpo.","forno":"Lugar no fogão onde se fazem os assados.","mando":"Determinação, mandado, ordem.","mano":"Irmão.","modo":"Jeito, maneira.","mofo":"Bolor.","mor":"Altar-(?): o principal da igreja.","morno":"Pouco quente.","namoro":"(?) rápido: flerte.","nora":"A esposa do filho ou filha.","norma":"Lei, regra.","odor":"Cheiro.","onda":"Pegar (?): surfar.","ornado":"Enfeitado, adornado.","roda":"(?)-gigante, presente em parques de diversão.","rodo":"A (?): à beça.","romano":"Pertencente ou relativo a Roma.","dar":"Transferir a posse de algo, gratuitamente, para outrem.","ano":"(?) bissexto, tem 366 dias.","aro":"Arco; argola; círculo; anel.","não":"Expressa negação.","ora":"Agora.","formando":"Aquele que está prestes a formar-se.","ado":"O leite fresco, recentemente ordenhado.","adro":"Espaço em volta das igrejas.","afro":"Relativo à etnia negra americana, originária da África.","amo":"Dono da casa (em relação aos criados).","amor":"Sentimento de gostar muito de outra pessoa ou coisa.","dor":"Sofrimento físico ou moral.","mão":"Extremidade do membro anterior dos primatas, capaz de manipular objetos.","mar":"Grande quantidade de água salgada que cobre parte do planeta Terra.","noa":"Hora canônica do ofício divino entre a sexta e as vésperas (correspondente às três horas da tarde).","nodo":"corpo arredondado.","ramo":"Divisão ou subdivisão de um caule (bot.).","romã":"Fruto da romãzeira.","domar":"Amansar, domesticar.","moda":"Tendência de consumo da atualidade.","mono":"Macaco, bugio.","nado":"Ato de nadar.","órfão":"Que perdeu o pai e a mãe ou um deles.","doma":"Ato, processo ou efeito de domar.","dono":"Possuidor de alguma coisa.","mofar":"Cobrir, encher de mofo."}}