{"slug":"daily-NPA4bx2D","word":"vermelha","words":["are","ave","ela","ele","ema","era","hem","lar","ler","lha","lhe","mãe","mal","mar","mel","ver","além","elar","erma","erva","hera","lema","leme","leva","leve","maré","mear","mera","ralé","real","relé","relê","vale","vela","vera","harém","haver","levar","melar","relva","valer","velar","velha","verme","elevar","remela","vermelha"],"definitions":{"ela":"(?) é Carioca, clássico da MPB.","elevar":"Alçar, erguer, levantar.","era":"Já (?): acabou.","haver":"Existir.","hera":"Deusa grega da família (mit.).","lar":"A casa de habitação (fig.).","leme":"Serve para direcionar barcos e aviões.","leva":"Lote, grupo.","levar":"Transportar consigo.","leve":"Que tem pouco peso.","mal":"(?)-agradecido: ingrato, desagradecido (bras.).","maré":"Movimento periódico de subida e descida das águas do mar.","ralé":"A camada mais baixa da sociedade.","real":"Que de fato existe, isto é, não é imaginário.","vale":"Depressão entre montes.","vela":"É usada em bolos de aniversário.","ver":"(?) para crer: atitude do cético.","mãe":"Progenitora, a que dá à luz.","are":"Unidade de medida de área equivalente a 100 metros quadrados.","ema":"Grande ave parecida com o avestruz.","lema":"Ideia expressa por uma frase que serve de guia ou de motivação.","além":"Mais adiante.","ave":"Animal bípede com penas.","elar":"Prender-se com elos.","ele":"Nome da letra do alfabeto latino representada por l, L.","erma":"Que está só ou desacompanhado (fem.).","ler":"Interpretar o que está escrito.","mar":"Grande quantidade de água salgada que cobre parte do planeta Terra.","mel":"Substância doce, espessa e viscosa elaborada pelas abelhas nas colmeias.","melar":"Tornar algo melado.","relé":"Dispositivo eletromecânico ou não, com inúmeras aplicações possíveis em comutação de contatos elétricos.","lha":"Pronome oblíquo feminino.","mera":"Simples; genuíno (fem.)."}}