{"slug":"daily-DeXJO4r2","word":"frieira","words":["are","eia","era","ira","rei","ria","rir","arre","eira","feia","fera","fiar","frei","fria","irar","irra","raer","rifa","feira","féria","ferir","frear","rifar","aferir","feriar","fieira","freira","frieira"],"definitions":{"aferir":"Avaliar, estimar.","era":"Já (?): acabou.","feira":"Local onde se mostram e vendem mercadorias.","fera":"A Bela e a (?)', conto infantil.","feriar":"Tirar férias.","ferir":"Causar ferimento a.","fiar":"Reduzir a fio.","freira":"Madre, monja.","ira":"Cólera, fúria, indignação.","rei":"Peça mais importante do jogo de xadrez.","rifa":"Sorteio de objetos por meio da loteria ou de bilhetes numerados.","rir":"(?) é o melhor remédio (dito).","are":"Unidade de medida de área equivalente a 100 metros quadrados.","arre":"Voz com que se tocam animais de carga.","eia":"Que serve para animar, excitar.","eira":"Porção de terreno plano e duro, ou laje, em que se secam cereais e legumes.","raer":"Rapar e juntar o sal nas salinas.","ria":"Enseada estreita, produto do alagamento de um vale fluvial em épocas geológicas pretéritas.","irar":"Provocar a ira de.","irra":"Interjeição que expressa um sentimento de desabafo.","feia":"Desprovido de beleza (fem.).","frear":"Diminuir a velocidade por meio de freios."}}