{"slug":"daily-APRQn582","word":"vítrea","words":["are","até","ave","eia","era","eta","ira","ita","itã","rei","ria","ter","tia","tri","ver","via","vir","arte","ater","avir","eira","eita","erva","iate","reta","tear","teia","tira","vate","veia","vera","vira","trave","treva","vetar","evitar","vítrea"],"definitions":{"até":"(?) logo, saudação de despedida.","era":"Já (?): acabou.","evitar":"Escapar-se de, esquivar-se de algo.","iate":"Embarcação luxuosa.","ira":"Cólera, fúria, indignação.","rei":"Peça mais importante do jogo de xadrez.","reta":"Linha, traço que segue sempre a mesma direção.","ter":"(?) os pés no chão: ser realista.","tia":"(?) Nastácia, personagem da obra de Monteiro Lobato.","tira":"Olhar não (?) pedaço (dito).","trave":"Tronco comprido e grosso que constitui a estrutura principal de uma construção.","veia":"Vaso do qual se dá o retorno do sangue para o coração (anat.).","ver":"(?) para crer: atitude do cético.","via":"(?) Láctea: galáxia da qual o Sistema Solar faz parte (astr.).","are":"Unidade de medida de área equivalente a 100 metros quadrados.","eia":"Que serve para animar, excitar.","eira":"Porção de terreno plano e duro, ou laje, em que se secam cereais e legumes.","eta":"Sétima letra do alfabeto grego.","ita":"Embarcação que fazia o percurso pela costa brasileira do norte e o sul do país.","arte":"Atividade criadora.","ater":"Impedir que prossiga.","ave":"Animal bípede com penas.","eita":"Expressa admiração.","itã":"Ornamento de pedra característico das urnas funerárias dos antigos povos aborígines.","ria":"Enseada estreita, produto do alagamento de um vale fluvial em épocas geológicas pretéritas.","tri":"Três vezes campeão.","vate":"Poeta, trovador.","vir":"Transportar-se para o local onde está o interlocutor.","vira":"Dança e música popular portuguesa."}}