{"slug":"daily-4eE0qwPD","word":"topógrafo","words":["aro","ato","opa","ora","pão","par","poá","por","pôr","pra","pro","pró","tão","afro","agro","apto","argo","ator","atro","faro","fato","fogo","fora","foro","foto","garo","gato","gota","grão","ogra","ogro","opar","opor","órfã","orto","pago","pato","poro","proa","rato","roga","rogo","rota","roto","tarô","toar","toga","topo","tora","toro","toró","farto","fator","fogão","frota","garfo","grafo","grato","grota","optar","órfão","órgão","parto","porão","porta","porto","potro","prato","rapto","topar","trago","trapo","tropa","garoto","grotão","portão","topógrafo"],"definitions":{"apto":"Capaz, habilitado.","ator":"Aquele que representa uma personagem no teatro ou no cinema.","farto":"Cheio, repleto.","fato":"Ação, coisa feita, acontecimento.","fator":"Cada termo da multiplicação (mat.).","fogão":"Aparelho doméstico para cozinhar e aquecer.","fora":"Bota-(?), festa de despedida.","frota":"Conjunto de navios de guerra ou mercantes.","garfo":"Utensílio de dois ou mais dentes que faz parte do talher.","garoto":"Menino (pop.).","grão":"Fruto ou semente das gramíneas.","ogro":"Monstro.","optar":"Fazer escolha.","pão":"Alimento à base de farinha amassada, fermentada e assada em forno.","par":"Diz-se dos números divisíveis por 2.","pôr":"(?) de lado: desprezar.","portão":"Porta grande.","prato":"Vasilha, normalmente de louça ou metal, em que se come ou se serve comida.","proa":"Parte dianteira do navio.","rogo":"Pedido, súplica.","rota":"Direção do navio.","topar":"Aceitar (gír.).","topo":"Ápice, cume, ponto mais elevado.","tora":"Grande tronco de madeira.","tropa":"Conjunto de soldados.","aro":"Arco; argola; círculo; anel.","atro":"De cor negra.","ora":"Agora.","tão":"Tanto, com tal intensidade.","grotão":"Grota enorme.","pago":"Cujo pagamento foi efetuado.","afro":"Relativo à etnia negra americana, originária da África.","agro":"Acre, azedo, ácido.","argo":"Homem muito perspicaz.","ato":"Algo que foi feito.","garo":"Molho, salmoura feita a partir de peixes menores ou restos de peixes.","opa":"Exprime surpresa, admiração ou indignação.","poá":"Bolinha.","por":"Exprime, entre outras relações, causa, modo, tempo, meio, lugar, qualidade, estado, preço, etc.","pra":"Forma sincopada de para.","pro":"Contração da preposição para e o artigo o.","pró":"A favor, em defesa.","rapto":"Ato ou efeito de raptar.","rato":"Pequeno roedor da família dos murídeos, gêneros Rattus.","roto":"Esburacado, rasgado.","toar":"Emitir som; soar.","toro":"Segmento de tronco de árvore.","gato":"Pequeno mamífero carnívoro doméstico da família dos felídeos.","órfão":"Que perdeu o pai e a mãe ou um deles.","toga":"Traje usado por magistrados.","opor":"Apresentar em oposição.","topógrafo":"Especialista em topografia."}}