{"slug":"daily-ym2QjPnJ","word":"execícios","words":["cio","cós","eco","eis","cios","coxé","ecos","eixo","seco","seio","sexo","césio","cisco","coice","eixos","seixo","coices","execício","execícios"],"definitions":{"eixo":"Peça cilíndrica que tem como função transmitir movimento de uma extremidade a outra.","seco":"Sem água ou umidade.","cio":"Período de maior apetite sexual e fertilidade de certos animais.","cós":"Pedaço de tecido que envolve a cintura em calças, saias, bermudas.","eis":"Aqui está.","coice":"Pancada defensiva que certos quadrúpedes desferem.","coxé":"Que coxeia.","eco":"Repetição de um som refletido por um corpo.","césio":"Elemento químico de número atômico 55 da família dos metais alcalinos."}}