{"slug":"daily-l2wjEM1D","word":"esquecer","words":["céu","cru","cus","eus","que","rés","rês","réu","ser","seu","céus","crus","quer","réus","sequer","esquecer"],"definitions":{"céu":"A (?) aberto: ao ar livre.","esquecer":"Perder da lembrança.","que":"Como?.","réu":"Acusado em juízo (jur.).","sequer":"Ao menos.","ser":"(?) Supremo: Deus.","rés":"Rente, raso.","rês":"Qualquer animal quadrúpede que se abate para a alimentação humana.","céus":"Firmamento (pl.).","cru":"Que não foi cozido.","cus":"Ânus (pl.).","quer":"Conjução com o valor de ou.","seu":"Pronome possessivo que corresponde à terceira pessoa gramatical."}}