{"slug":"daily-vPo86MeZ","word":"locutor","words":["cor","cru","oco","rol","ulo","colo","coro","coto","cotó","loto","luto","octo","olor","orto","ouro","rolo","roto","toco","tolo","toro","toró","urco","cloro","couro","couto","culto","curto","louco","louro","lucro","outro","rouco","touro","troco","troço","truco","turco","cultor","oculto","rótulo","locutor"],"definitions":{"colo":"Pescoço.","cor":"Coloração predominante de algo.","couro":"Pele espessa de certos animais.","locutor":"Pessoa que narra algum tipo de evento.","louco":"Que perdeu a razão.","luto":"A morte (fig.).","oculto":"Escondido, encoberto.","outro":"Diferente da pessoa ou da coisa que foi mencionada.","rolo":"Confusão; desordem (bras. gír.).","tolo":"Sem inteligência ou juízo.","cru":"Que não foi cozido.","oco":"Que não tem miolo.","rol":"Lista; relação.","roto":"Esburacado, rasgado.","toro":"Segmento de tronco de árvore.","ulo":"Grito de sofrimento, aflição.","loto":"Modalidade de loteria."}}