{"slug":"daily-y2aglw6e","word":"pelourinho","words":["elo","íon","ipê","lei","ler","léu","lhe","lho","olé","per","pio","por","pôr","pré","pro","pró","rei","réu","ril","rio","rol","ulo","uno","eril","euro","hino","íleo","iole","nulo","óleo","olho","olor","ópio","opor","ouro","pelo","pêlo","peru","píer","pino","pior","pneu","pólo","poro","prol","pulo","purê","puro","rino","rolê","rolo","rulê","unir","hélio","herói","lenho","linho","loiro","louro","pinel","pinho","pleno","polir","pônei","porei","prelo","prole","punho","punir","reino","oleiro","penhor","piolho","pueril","urinol","olheiro","poleiro","pulinho","repolho","pelourinho"],"definitions":{"hélio":"Gás usado em balões de festa.","herói":"Indivíduo notável positivamente por seus feitos e/ou capacidades.","hino":"Canto de exaltação, por exemplo, de times, nações, heróis.","nulo":"Que não é válido.","oleiro":"Pessoa que fabrica ou decora cerâmica.","óleo":"Lubrificante de motores.","olheiro":"Pessoa que procura novos talentos ainda não reconhecidos.","olho":"Especialidade do oftalmologista.","penhor":"Objeto que se dá como garantia de um contrato ou dívida.","pio":"A voz da coruja.","pior":"Na (?): na fossa (gír.).","pleno":"Que está completo, inteiro.","pneu":"Gordura na cintura (pop.).","poleiro":"Vara onde as aves pousam e dormem.","pôr":"(?) de lado: desprezar.","pré":"(?)-nupcial: que se dá antes do casamento.","prol":"Em (?) de: em favor de.","pueril":"Relativo ou pertencente a criança.","punho":"A parte proximal da mão que se articula com o antebraço.","puro":"Sem mistura.","rei":"Peça mais importante do jogo de xadrez.","reino":"Estado que tem por soberano um rei ou uma rainha.","repolho":"Variedade de couve.","réu":"Acusado em juízo (jur.).","rio":"(?) Branco, a capital do Acre.","rolo":"Confusão; desordem (bras. gír.).","urinol":"Mictório.","íon":"Átomo ou grupo atômico eletricamente carregado.","elo":"Cada uma das argolas de uma corrente.","iole":"Embarcação comprida e estreita movida a remo.","ipê":"Árvore leguminosa com madeira avermelhada e floração de cor muito viva.","lei":"Regra imposta pela autoridade estatal.","ler":"Interpretar o que está escrito.","olé":"Drible desconcertante dado a alguém.","per":"Por.","pinho":"Pinheiro.","por":"Exprime, entre outras relações, causa, modo, tempo, meio, lugar, qualidade, estado, preço, etc.","pro":"Contração da preposição para e o artigo o.","pró":"A favor, em defesa.","ril":"Dança de origem escocesa.","rol":"Lista; relação.","rolê":"Qualquer coisa em forma de rolo.","ulo":"Grito de sofrimento, aflição.","uno":"Único.","eril":"Feito ou recoberto de bronze, cobre ou latão.","íleo":"Parte final do intestino delgado (anat.).","lho":"Pronome oblíquo masculino.","rino":"Palavra que indica nariz (med.).","linho":"Planta da família das Lináceas, de que se extrai o óleo de linhaça.","euro":"Moeda única dos países da União Europeia.","lenho":"Tronco ou peça grossa de madeira.","opor":"Apresentar em oposição.","pulo":"Ato de pular."}}